flake8_pep518/__init__.py
flake8_pep518/main.py
flake8_pep518/mixins.py
flake8_pep518-0.2.0.dist-info/entry_points.txt
flake8_pep518-0.2.0.dist-info/WHEEL
flake8_pep518-0.2.0.dist-info/METADATA
flake8_pep518-0.2.0.dist-info/license_files/LICENSE
flake8_pep518-0.2.0.dist-info/RECORD
