Metadata-Version: 2.1
Name: flake8-pep518
Version: 0.2.0
Summary: Flake8 plugin that allows specifying config in pyproject.toml.
License: MIT
Keywords: flake8,pep518,pyproject,plugin,config
Author-email: aleksul <me@aleksul.space>
Requires-Python: >=3.7
Classifier: Development Status :: 3 - Alpha
Classifier: Environment :: Plugins
Classifier: Framework :: Flake8
Requires-Dist: flake8>=4.0.0, <6.0.0
Requires-Dist: tomli>=2.0.1,<3.0.0; python_version < "3.11"
Project-URL: homepage, https://github.com/aleksul/flake8-pep518/
Project-URL: repository, https://github.com/aleksul/flake8-pep518/
